resources/99-eyes17-pip.rules
resources/__init__.py
resources/sispmctl.conf
seelabv2/Peripherals.py
seelabv2/__init__.py
seelabv2/achan.py
seelabv2/commands_proto.py
seelabv2/eyemath17.py
seelabv2/eyeplot17.py
seelabv2/eyes.py
seelabv2/packet_handler.py
seelabv2/sensorlist.py
seelabv2/SENSORS/AD7718_class.py
seelabv2/SENSORS/AD9833.py
seelabv2/SENSORS/ADS1115.py
seelabv2/SENSORS/ADS1248.py
seelabv2/SENSORS/BH1750.py
seelabv2/SENSORS/BMP180.py
seelabv2/SENSORS/ComplementaryFilter.py
seelabv2/SENSORS/HMC5883L.py
seelabv2/SENSORS/Kalman.py
seelabv2/SENSORS/MF522.py
seelabv2/SENSORS/MLX90614.py
seelabv2/SENSORS/MPU6050.py
seelabv2/SENSORS/MPU925x.py
seelabv2/SENSORS/SHT21.py
seelabv2/SENSORS/SSD1306.py
seelabv2/SENSORS/TSL2561.py
seelabv2/SENSORS/__init__.py
seelabv2/SENSORS/supported.py
seelabv2GUI/BHCurve.py
seelabv2GUI/LA.py
seelabv2GUI/MPU6050.py
seelabv2GUI/QtVersion.py
seelabv2GUI/RCtransient.py
seelabv2GUI/RLCsteadystate.py
seelabv2GUI/RLCtransient.py
seelabv2GUI/RLtransient.py
seelabv2GUI/XYplot.py
seelabv2GUI/XYplot2.py
seelabv2GUI/__init__.py
seelabv2GUI/advanced_logger.py
seelabv2GUI/diodeIV.py
seelabv2GUI/driven-pendulum.py
seelabv2GUI/drivenRodPendulum.py
seelabv2GUI/dust_sensor.py
seelabv2GUI/editor.py
seelabv2GUI/filterCircuit.py
seelabv2GUI/i2cLogger.py
seelabv2GUI/induction.py
seelabv2GUI/language.py
seelabv2GUI/lightsensorlogger.py
seelabv2GUI/logger.py
seelabv2GUI/main.py
seelabv2GUI/newtons_laws.py
seelabv2GUI/npnCEout.py
seelabv2GUI/pendulumVelocity.py
seelabv2GUI/plotIV.py
seelabv2GUI/pnpCEout.py
seelabv2GUI/pt100.py
seelabv2GUI/pythonSyntax.py
seelabv2GUI/renumberHelpFiles.py
seelabv2GUI/renumberIndex.py
seelabv2GUI/rodPendulum.py
seelabv2GUI/saveProfile.py
seelabv2GUI/scope.py
seelabv2GUI/server.html
seelabv2GUI/server.py
seelabv2GUI/server.webpage.html
seelabv2GUI/soundBeats.py
seelabv2GUI/soundFreqResp.py
seelabv2GUI/soundVelocity.py
seelabv2GUI/sr04dist.py
seelabv2GUI/sr04dist_fft.py
seelabv2GUI/terminal.py
seelabv2GUI/tof.py
seelabletv2-1.0.0.dist-info/LICENSE
seelabletv2-1.0.0.dist-info/METADATA
seelabletv2-1.0.0.dist-info/WHEEL
seelabletv2-1.0.0.dist-info/entry_points.txt
seelabletv2-1.0.0.dist-info/top_level.txt
seelabletv2-1.0.0.dist-info/RECORD
