Metadata-Version: 2.1
Name: seelabletv2
Version: 1.0.0
Summary: Python package for seelablet
Home-page: https://github.com/csparkresearch/seelablet
Author: Jithin B.P
Author-email: jithinbp@gmail.com
License: UNKNOWN
Project-URL: Source, https://github.com/expeyes/expeyes-programs
Project-URL: Read The Docs, https://expeyes.in
Project-URL: Buy Hardware, https://csparkresearch.in/expeyes17
Keywords: seelablet v2 data-acquisition lab-at-home oscilloscope waveform-generator sensors physics
Platform: UNKNOWN
Classifier: Development Status :: 5 - Production/Stable
Classifier: Intended Audience :: Education
Classifier: Programming Language :: Python :: 3
Classifier: License :: OSI Approved :: MIT License
Classifier: Operating System :: OS Independent
Requires-Python: >=3
Requires-Dist: pyserial
Requires-Dist: numpy
Requires-Dist: scipy
Requires-Dist: PyQt5
Requires-Dist: pyqtwebengine
Requires-Dist: pyqtgraph
Requires-Dist: matplotlib
